{
    "Raw data Info.": {
        "raw_data_ID": "L-210917_G04_D_WS-09_002",
        "location_ID": "G04",
        "process_ID": "D",
        "situation_ID": "WS-09",
        "situation_description": "운반수레, 롤테이너, 핸드파렛트카에 적재할 때 개별물류가 안정적으로 적재된 상태 ",
        "copyrighter": "㈜미디어그룹사람과숲",
        "resolution": [
            1920,
            1080
        ],
        "date": "2021-09-17",
        "start_time": "10:40:00",
        "end_time": "10:41:13",
        "length": "73",
        "lux": 150,
        "fps": 30,
        "f-stop": "F/4.0",
        "exposure_time": "1/80",
        "device": 1,
        "file_extension": "mp4"
    },
    "Source data Info.": {
        "source_data_ID": "L-210917_G04_D_WS-09_002_0038",
        "file_extension": "jpg"
    },
    "Learning data info.": {
        "path": "./작업환경/부가가치서비스/작업상황(WS)",
        "json_data_ID": "L-210917_G04_D_WS-09_002_0038",
        "file_extension": "json",
        "annotation": [
            {
                "class_id": "SO-13",
                "type": "polygon",
                "coord": [
                    [
                        1338.3699658187,
                        1080
                    ],
                    [
                        1338.3699658187,
                        1080
                    ]
                ]
            },
            {
                "class_id": "SO-03",
                "type": "box",
                "coord": [
                    972.66718838827,
                    521.16469169779,
                    193.16544092881,
                    182.48904972367
                ]
            },
            {
                "class_id": "WO-07",
                "type": "box",
                "coord": [
                    885.06986748039,
                    539.7860662811,
                    387.54618688063,
                    289.3908459203
                ]
            },
            {
                "class_id": "SO-02",
                "type": "box",
                "coord": [
                    1198.2623346147,
                    403.90396626694,
                    513.64191763736,
                    162.3483910857
                ]
            },
            {
                "class_id": "WO-04",
                "type": "box",
                "coord": [
                    1877.2447381444,
                    412.86498854975,
                    42.755261855569,
                    97.097046609373
                ]
            },
            {
                "class_id": "SO-02",
                "type": "box",
                "coord": [
                    0,
                    298.74484901909,
                    713.9110268402,
                    465.66473447148
                ]
            },
            {
                "class_id": "WO-01",
                "type": "box",
                "coord": [
                    721.63757119043,
                    286.89878952027,
                    195.22031199692,
                    557.33212847587
                ]
            },
            {
                "class_id": "SO-03",
                "type": "box",
                "coord": [
                    1093.7683958307,
                    602.23275672429,
                    154.76567243586,
                    170.67341237829
                ]
            }
        ]
    }
}