{
    "Raw data Info.": {
        "raw_data_ID": "L-210916_G03_D_WS-09_001",
        "location_ID": "G03",
        "process_ID": "D",
        "situation_ID": "WS-09",
        "situation_description": "운반수레, 롤테이너, 핸드파렛트카에 적재할 때 개별물류가 안정적으로 적재된 상태",
        "copyrighter": "㈜미디어그룹사람과숲",
        "resolution": [
            1920,
            1080
        ],
        "date": "2021-09-16",
        "start_time": "13:45:00",
        "end_time": "13:46:05",
        "length": "65",
        "lux": 150,
        "fps": 30,
        "f-stop": "F/2.8",
        "exposure_time": "1/60",
        "device": 1,
        "file_extension": "mp4"
    },
    "Source data Info.": {
        "source_data_ID": "L-210916_G03_D_WS-09_001_0020",
        "file_extension": "jpg"
    },
    "Learning data info.": {
        "path": "./작업환경/부가가치서비스/작업상황(WS)",
        "json_data_ID": "L-210916_G03_D_WS-09_001_0020",
        "file_extension": "json",
        "annotation": [
            {
                "class_id": "SO-03",
                "type": "box",
                "coord": [
                    802.6099019453,
                    401.71678373069,
                    143.6783966845,
                    111.92196419024
                ]
            },
            {
                "class_id": "SO-03",
                "type": "box",
                "coord": [
                    807.72914318095,
                    491.08804413829,
                    139.93544280475,
                    87.589416121431
                ]
            },
            {
                "class_id": "WO-07",
                "type": "box",
                "coord": [
                    771.85662804177,
                    419.17953953513,
                    222.44784460761,
                    225.79034296381
                ]
            },
            {
                "class_id": "WO-01",
                "type": "box",
                "coord": [
                    775.9229407017,
                    230.37367998876,
                    131.46001815602,
                    330.85453849636
                ]
            },
            {
                "class_id": "SO-13",
                "type": "polygon",
                "coord": [
                    [
                        542.3169247225,
                        527.57318074293
                    ],
                    [
                        930.81910699456,
                        523.72928226985
                    ],
                    [
                        947.47749723266,
                        531.19980548221
                    ],
                    [
                        993.29915315361,
                        553.68158344687
                    ],
                    [
                        1084.4276227408,
                        593.66826829569
                    ],
                    [
                        1190.6583517662,
                        641.20609429971
                    ],
                    [
                        1300.5535963248,
                        686.46892904116
                    ],
                    [
                        1347.5190033045,
                        705.58274971521
                    ],
                    [
                        1447.1839627927,
                        749.27150143366
                    ],
                    [
                        1533.8825860588,
                        785.49301996956
                    ],
                    [
                        1613.2783132853,
                        820.35761677231
                    ],
                    [
                        1692.3482080224,
                        854.02749201651
                    ],
                    [
                        1767.9424940579,
                        886.61124285428
                    ],
                    [
                        1858.6339365136,
                        926.25480419836
                    ],
                    [
                        1920,
                        950.14955232678
                    ],
                    [
                        1920,
                        1079.3632168028
                    ],
                    [
                        864.80649558559,
                        1079.9135951375
                    ],
                    [
                        811.51505756317,
                        990.16659543598
                    ],
                    [
                        776.84848606391,
                        931.98853953906
                    ],
                    [
                        729.65388996787,
                        849.4409115507
                    ],
                    [
                        698.07641913258,
                        801.7314636137
                    ],
                    [
                        671.30419766616,
                        758.99889854118
                    ],
                    [
                        663.23822569243,
                        748.87351087925
                    ],
                    [
                        653.45608144584,
                        734.80096016669
                    ],
                    [
                        638.18217649888,
                        705.11126134481
                    ],
                    [
                        625.31093158831,
                        681.59977535027
                    ],
                    [
                        605.57499758627,
                        650.8803802825
                    ],
                    [
                        585.32422132956,
                        620.16099110671
                    ],
                    [
                        567.30445960039,
                        589.95643826989
                    ],
                    [
                        554.94039683428,
                        563.76161153873
                    ],
                    [
                        550.18997033461,
                        550.10245018794
                    ],
                    [
                        546.36721914813,
                        538.98627966223
                    ],
                    [
                        542.3169247225,
                        527.57318074293
                    ]
                ]
            }
        ]
    }
}