{
    "Raw data Info.": {
        "raw_data_ID": "L-210917_G04_D_WS-09_002",
        "location_ID": "G04",
        "process_ID": "D",
        "situation_ID": "WS-09",
        "situation_description": "운반수레, 롤테이너, 핸드파렛트카에 적재할 때 개별물류가 안정적으로 적재된 상태 ",
        "copyrighter": "㈜미디어그룹사람과숲",
        "resolution": [
            1920,
            1080
        ],
        "date": "2021-09-17",
        "start_time": "10:40:00",
        "end_time": "10:41:13",
        "length": "73",
        "lux": 150,
        "fps": 30,
        "f-stop": "F/4.0",
        "exposure_time": "1/80",
        "device": 1,
        "file_extension": "mp4"
    },
    "Source data Info.": {
        "source_data_ID": "L-210917_G04_D_WS-09_002_0027",
        "file_extension": "jpg"
    },
    "Learning data info.": {
        "path": "./작업환경/부가가치서비스/작업상황(WS)",
        "json_data_ID": "L-210917_G04_D_WS-09_002_0027",
        "file_extension": "json",
        "annotation": [
            {
                "class_id": "WO-01",
                "type": "box",
                "coord": [
                    1371.3752488564,
                    278.46423626899,
                    190.34714553454,
                    529.21197647867
                ]
            },
            {
                "class_id": "SO-02",
                "type": "box",
                "coord": [
                    904.78158215759,
                    430.47753446671,
                    233.06058091159,
                    157.28275136559
                ]
            },
            {
                "class_id": "SO-02",
                "type": "box",
                "coord": [
                    0,
                    299.70278247877,
                    711.57504765458,
                    465.66473447148
                ]
            },
            {
                "class_id": "SO-02",
                "type": "box",
                "coord": [
                    1533.4106459002,
                    403.46202858555,
                    176.66929347757,
                    162.3483910857
                ]
            },
            {
                "class_id": "WO-04",
                "type": "box",
                "coord": [
                    1877.2447381444,
                    412.40489113278,
                    42.755261855569,
                    96.62985077225
                ]
            },
            {
                "class_id": "WO-07",
                "type": "box",
                "coord": [
                    1081.933684089,
                    545.9233189456,
                    386.51023015792,
                    305.17139187371
                ]
            },
            {
                "class_id": "SO-03",
                "type": "box",
                "coord": [
                    1177.2135669717,
                    525.54892261319,
                    241.69621342336,
                    179.68591342574
                ]
            },
            {
                "class_id": "SO-03",
                "type": "box",
                "coord": [
                    1103.0332707142,
                    596.11869254985,
                    253.18181418523,
                    200.84266151893
                ]
            },
            {
                "class_id": "SO-13",
                "type": "polygon",
                "coord": [
                    [
                        1266.3699658187,
                        1080
                    ],
                    [
                        1266.3699658187,
                        1080
                    ]
                ]
            },
            {
                "class_id": "SO-02",
                "type": "box",
                "coord": [
                    1199.4114486789,
                    423.74101554674,
                    235.13646530588,
                    129.23244324094
                ]
            }
        ]
    }
}