{
    "Raw data Info.": {
        "raw_data_ID": "L-210916_G03_D_WS-09_001",
        "location_ID": "G03",
        "process_ID": "D",
        "situation_ID": "WS-09",
        "situation_description": "운반수레, 롤테이너, 핸드파렛트카에 적재할 때 개별물류가 안정적으로 적재된 상태",
        "copyrighter": "㈜미디어그룹사람과숲",
        "resolution": [
            1920,
            1080
        ],
        "date": "2021-09-16",
        "start_time": "13:45:00",
        "end_time": "13:46:05",
        "length": "65",
        "lux": 150,
        "fps": 30,
        "f-stop": "F/2.8",
        "exposure_time": "1/60",
        "device": 1,
        "file_extension": "mp4"
    },
    "Source data Info.": {
        "source_data_ID": "L-210916_G03_D_WS-09_001_0110",
        "file_extension": "jpg"
    },
    "Learning data info.": {
        "path": "./작업환경/부가가치서비스/작업상황(WS)",
        "json_data_ID": "L-210916_G03_D_WS-09_001_0110",
        "file_extension": "json",
        "annotation": [
            {
                "class_id": "WO-01",
                "type": "box",
                "coord": [
                    887.9074648312,
                    191.45650368545,
                    199.33593656601,
                    569.07704523746
                ]
            },
            {
                "class_id": "WO-07",
                "type": "box",
                "coord": [
                    797.94460228247,
                    468.30693084531,
                    282.28459963132,
                    256.54156698329
                ]
            },
            {
                "class_id": "SO-03",
                "type": "box",
                "coord": [
                    846.57209184299,
                    423.28170857011,
                    174.8125411866,
                    115.42358386188
                ]
            },
            {
                "class_id": "SO-03",
                "type": "box",
                "coord": [
                    848.23984067669,
                    528.27475993812,
                    161.87987031919,
                    111.07443563922
                ]
            },
            {
                "class_id": "SO-13",
                "type": "polygon",
                "coord": [
                    [
                        541.67431241961,
                        526.84332640967
                    ],
                    [
                        938.74500503074,
                        526.50131488399
                    ],
                    [
                        1135.9155341867,
                        617.19190412612
                    ],
                    [
                        1309.4200254079,
                        689.2709005866
                    ],
                    [
                        1512.3773136171,
                        776.31338952198
                    ],
                    [
                        1585.3649099064,
                        805.63876714043
                    ],
                    [
                        1665.3037012256,
                        841.69810041737
                    ],
                    [
                        1780.215714213,
                        890.79094148724
                    ],
                    [
                        1877.5325042935,
                        931.84646716993
                    ],
                    [
                        1919.782753481,
                        951.2881009437
                    ],
                    [
                        1920,
                        1079.5594451762
                    ],
                    [
                        863.31774353474,
                        1079.6591270926
                    ],
                    [
                        836.4491902336,
                        1032.6406930375
                    ],
                    [
                        807.64192169914,
                        983.08126454523
                    ],
                    [
                        781.70173061643,
                        938.98293236139
                    ],
                    [
                        748.79863849014,
                        881.77797372455
                    ],
                    [
                        701.96977240046,
                        806.27835534446
                    ],
                    [
                        678.76010850493,
                        770.78125043234
                    ],
                    [
                        661.14808674668,
                        747.84465062413
                    ],
                    [
                        642.8534167861,
                        713.84934075181
                    ],
                    [
                        631.24859421293,
                        689.82052636921
                    ],
                    [
                        613.09044639314,
                        659.51145943465
                    ],
                    [
                        591.79219558921,
                        626.47184200221
                    ],
                    [
                        571.85919431698,
                        594.93401960958
                    ],
                    [
                        559.02562560371,
                        570.76868309247
                    ],
                    [
                        550.97051931002,
                        554.3853988544
                    ],
                    [
                        541.67431241961,
                        526.84332640967
                    ]
                ]
            }
        ]
    }
}